setup.py
hkteam/__init__.py
hkteam/cFuntion.py
hkteam.egg-info/PKG-INFO
hkteam.egg-info/SOURCES.txt
hkteam.egg-info/dependency_links.txt
hkteam.egg-info/requires.txt
hkteam.egg-info/top_level.txt